MANIFEST.in
README.md
setup.py
qldbshell/__init__.py
qldbshell/__main__.py
qldbshell/decorators.py
qldbshell/outcome.py
qldbshell/qldb_shell.py
qldbshell/shell_transaction.py
qldbshell/shell_utils.py
qldbshell.egg-info/PKG-INFO
qldbshell.egg-info/SOURCES.txt
qldbshell.egg-info/dependency_links.txt
qldbshell.egg-info/entry_points.txt
qldbshell.egg-info/requires.txt
qldbshell.egg-info/top_level.txt
qldbshell/deps/__init__.py
qldbshell/deps/amazon-qldb-driver-python/.git
qldbshell/deps/amazon-qldb-driver-python/.gitignore
qldbshell/deps/amazon-qldb-driver-python/CHANGELOG.md
qldbshell/deps/amazon-qldb-driver-python/CODE_OF_CONDUCT.md
qldbshell/deps/amazon-qldb-driver-python/LICENSE
qldbshell/deps/amazon-qldb-driver-python/NOTICE
qldbshell/deps/amazon-qldb-driver-python/README.md
qldbshell/deps/amazon-qldb-driver-python/THIRD-PARTY
qldbshell/deps/amazon-qldb-driver-python/__init__.py
qldbshell/deps/amazon-qldb-driver-python/buildspec.yml
qldbshell/deps/amazon-qldb-driver-python/requirements-docs.txt
qldbshell/deps/amazon-qldb-driver-python/requirements.txt
qldbshell/deps/amazon-qldb-driver-python/setup.py
qldbshell/deps/amazon-qldb-driver-python/.github/workflows/pythonapp.yml
qldbshell/deps/amazon-qldb-driver-python/docs/Makefile
qldbshell/deps/amazon-qldb-driver-python/docs/make.bat
qldbshell/deps/amazon-qldb-driver-python/docs/source/conf.py
qldbshell/deps/amazon-qldb-driver-python/docs/source/index.rst
qldbshell/deps/amazon-qldb-driver-python/docs/source/_static/404.html
qldbshell/deps/amazon-qldb-driver-python/docs/source/_static/css/custom.css
qldbshell/deps/amazon-qldb-driver-python/docs/source/_templates/globaltoc.html
qldbshell/deps/amazon-qldb-driver-python/docs/source/_templates/layout.html
qldbshell/deps/amazon-qldb-driver-python/docs/source/guide/cookbook.rst
qldbshell/deps/amazon-qldb-driver-python/docs/source/guide/getting_started.rst
qldbshell/deps/amazon-qldb-driver-python/docs/source/guide/installation.rst
qldbshell/deps/amazon-qldb-driver-python/docs/source/reference/index.rst
qldbshell/deps/amazon-qldb-driver-python/docs/source/reference/communication/session_client.rst
