Metadata-Version: 2.1
Name: qldbshell
Version: 1.2.0
Summary: A basic CLI for interacting with Amazon QLDB
Home-page: UNKNOWN
Author: Amazon Web Services
License: Apache License 2.0
Platform: UNKNOWN
